CHANGELOG.txt
LICENCE.txt
MANIFEST.in
README.txt
setup.py
Encode_URL.egg-info/PKG-INFO
Encode_URL.egg-info/SOURCES.txt
Encode_URL.egg-info/dependency_links.txt
Encode_URL.egg-info/requires.txt
Encode_URL.egg-info/top_level.txt
encodeurl/__init__.py
encodeurl/__version__.py
encodeurl/encode.py
venv/Lib/site-packages/easy_install.py
venv/Lib/site-packages/_distutils_hack/__init__.py
venv/Lib/site-packages/_distutils_hack/override.py
venv/Lib/site-packages/certifi/__init__.py
venv/Lib/site-packages/certifi/__main__.py
venv/Lib/site-packages/certifi/core.py
venv/Lib/site-packages/certifi-2020.12.5.dist-info/top_level.txt
venv/Lib/site-packages/chardet/__init__.py
venv/Lib/site-packages/chardet/big5freq.py
venv/Lib/site-packages/chardet/big5prober.py
venv/Lib/site-packages/chardet/chardistribution.py
venv/Lib/site-packages/chardet/charsetgroupprober.py
venv/Lib/site-packages/chardet/charsetprober.py
venv/Lib/site-packages/chardet/codingstatemachine.py
venv/Lib/site-packages/chardet/compat.py
venv/Lib/site-packages/chardet/cp949prober.py
venv/Lib/site-packages/chardet/enums.py
venv/Lib/site-packages/chardet/escprober.py
venv/Lib/site-packages/chardet/escsm.py
venv/Lib/site-packages/chardet/eucjpprober.py
venv/Lib/site-packages/chardet/euckrfreq.py
venv/Lib/site-packages/chardet/euckrprober.py
venv/Lib/site-packages/chardet/euctwfreq.py
venv/Lib/site-packages/chardet/euctwprober.py
venv/Lib/site-packages/chardet/gb2312freq.py
venv/Lib/site-packages/chardet/gb2312prober.py
venv/Lib/site-packages/chardet/hebrewprober.py
venv/Lib/site-packages/chardet/jisfreq.py
venv/Lib/site-packages/chardet/jpcntx.py
venv/Lib/site-packages/chardet/langbulgarianmodel.py
venv/Lib/site-packages/chardet/langcyrillicmodel.py
venv/Lib/site-packages/chardet/langgreekmodel.py
venv/Lib/site-packages/chardet/langhebrewmodel.py
venv/Lib/site-packages/chardet/langhungarianmodel.py
venv/Lib/site-packages/chardet/langthaimodel.py
venv/Lib/site-packages/chardet/langturkishmodel.py
venv/Lib/site-packages/chardet/latin1prober.py
venv/Lib/site-packages/chardet/mbcharsetprober.py
venv/Lib/site-packages/chardet/mbcsgroupprober.py
venv/Lib/site-packages/chardet/mbcssm.py
venv/Lib/site-packages/chardet/sbcharsetprober.py
venv/Lib/site-packages/chardet-3.0.4.dist-info/entry_points.txt
venv/Lib/site-packages/chardet-3.0.4.dist-info/top_level.txt
venv/Lib/site-packages/idna-2.10.dist-info/top_level.txt
venv/Lib/site-packages/pip-20.3.1.dist-info/LICENSE.txt
venv/Lib/site-packages/pip-20.3.1.dist-info/entry_points.txt
venv/Lib/site-packages/pip-20.3.1.dist-info/top_level.txt
venv/Lib/site-packages/requests-2.25.0.dist-info/top_level.txt
venv/Lib/site-packages/setuptools-51.0.0.dist-info/dependency_links.txt
venv/Lib/site-packages/setuptools-51.0.0.dist-info/entry_points.txt
venv/Lib/site-packages/setuptools-51.0.0.dist-info/top_level.txt
venv/Lib/site-packages/urllib3-1.26.2.dist-info/LICENSE.txt
venv/Lib/site-packages/urllib3-1.26.2.dist-info/top_level.txt
