Metadata-Version: 1.1
Name: EncodeURL
Version: 1.0.1
Summary: Encode url
Home-page: UNKNOWN
Author: Manoj Sitapara
Author-email: manojsitapara@gmail.com
License: MIT
Keywords: Encode
Platform: UNKNOWN
Classifier: Development Status :: 5 - Production/Stable
Classifier: Intended Audience :: Education
Classifier: Operating System :: Microsoft :: Windows :: Windows 10
Classifier: License :: OSI Approved :: MIT License
Classifier: Programming Language :: Python :: 3
